safeprint/__init__.py
safeprint/version.py
safeprint-0.2.0.dist-info/DESCRIPTION.rst
safeprint-0.2.0.dist-info/METADATA
safeprint-0.2.0.dist-info/RECORD
safeprint-0.2.0.dist-info/WHEEL
safeprint-0.2.0.dist-info/entry_points.txt
safeprint-0.2.0.dist-info/metadata.json
safeprint-0.2.0.dist-info/top_level.txt
