Metadata-Version: 2.0
Name: safeprint
Version: 0.2.0
Summary: A printer suppressing UnicodeEncodeError
Home-page: https://github.com/eight04/safeprint
Author: eight
Author-email: eight04@gmail.com
License: MIT
Keywords: windows cmd unicode print
Platform: UNKNOWN
Classifier: Development Status :: 5 - Production/Stable
Classifier: Environment :: Console
Classifier: Environment :: Win32 (MS Windows)
Classifier: Intended Audience :: Developers
Classifier: License :: OSI Approved :: MIT License
Classifier: Natural Language :: Chinese (Traditional)
Classifier: Operating System :: Microsoft :: Windows :: Windows 7
Classifier: Programming Language :: Python :: 2.7
Classifier: Programming Language :: Python :: 3.5
Classifier: Programming Language :: Python :: 3.6
Classifier: Topic :: Terminals
Requires-Dist: win-unicode-console (>=0.4)
